blastwrapper/__init__.py
blastwrapper-0.1.0.dist-info/LICENSE
blastwrapper-0.1.0.dist-info/METADATA
blastwrapper-0.1.0.dist-info/WHEEL
blastwrapper-0.1.0.dist-info/RECORD
