Metadata-Version: 2.3
Name: blastwrapper
Version: 0.1.0
Summary: A wrapper for submitting and retrieving BLAST queries
Author: marcellobeltrami
Author-email: your.email@example.com
Requires-Python: >=3.10,<4.0
Classifier: Programming Language :: Python :: 3
Classifier: Programming Language :: Python :: 3.10
Classifier: Programming Language :: Python :: 3.11
Classifier: Programming Language :: Python :: 3.12
Classifier: Programming Language :: Python :: 3.13
Requires-Dist: requests (>=2.32.3,<3.0.0)
